Workbook
Name WACC: Assumptions!$B$26
Name Current_Share_Price: Assumptions!$B$32
Name Diluted_Shares: Assumptions!$B$33
Name Terminal_Growth_Rate: Assumptions!$B$29

Sheet Cover
A1: DCF VALUATION MODEL
A4: Company Name | B4: NVIDIA Corporation
A5: Ticker | B5: NVDA
A6: Currency | B6: USD
A7: Analyst | B7: Equity Research Associate (NVDA Project)
A8: Valuation Date | B8: =TODAY() -> 46227
A10: MODEL NAVIGATION
A11: Assumptions | B11: Central inputs: forecast drivers, WACC build, terminal growth, valuation inputs. Change the model here — everywhere else pulls from this sheet.
A12: Historical Financials | B12: 5 years of historical financial statement data feeding the forecast base year.
A13: Forecast | B13: 5-year explicit projection of revenue, margins, and unlevered free cash flow (FCFF).
A14: DCF Valuation | B14: Discounts FCFF and terminal value to derive enterprise value, equity value, and intrinsic value per share.
A15: Sensitivity Analysis | B15: WACC x Terminal Growth Rate grid showing intrinsic value per share under different scenarios.
A16: Charts | B16: Revenue/FCFF trend and intrinsic value vs. market price visualizations.

Sheet Assumptions
A1: ASSUMPTIONS
A4: FORECAST DRIVERS (5-YEAR EXPLICIT PERIOD)
B5: Year 1 | C5: Year 2 | D5: Year 3 | E5: Year 4 | F5: Year 5
A6: Revenue Growth % | B6: 0.6 | C6: 0.35 | D6: 0.22 | E6: 0.15 | F6: 0.1
A7: Operating (EBIT) Margin % | B7: 0.61 | C7: 0.6 | D7: 0.58 | E7: 0.56 | F7: 0.55
A8: Tax Rate % | B8: 0.165 | C8: 0.17 | D8: 0.175 | E8: 0.18 | F8: 0.19
A9: CapEx (% of Revenue) | B9: 0.028 | C9: 0.03 | D9: 0.032 | E9: 0.033 | F9: 0.035
A10: D&A (% of Revenue) | B10: 0.014 | C10: 0.015 | D10: 0.016 | E10: 0.017 | F10: 0.018
A11: Increase in Net Working Capital (% of Revenue) | B11: 0.06 | C11: 0.055 | D11: 0.05 | E11: 0.045 | F11: 0.04
A13: WACC BUILD
A14: Risk-Free Rate | B14: 0.045
A15: Equity Risk Premium | B15: 0.0475
A16: Levered Beta | B16: 1.5
A17: Cost of Equity (CAPM) | B17: =B14+B16*B15 -> 0.11625
A18: Pre-Tax Cost of Debt | B18: 0.03
A19: Marginal Tax Rate (for WACC) | B19: 0.21
A20: After-Tax Cost of Debt | B20: =B18*(1-B19) -> 0.0237
A21: Market Value of Equity | B21: 5106270
A22: Market Value of Debt | B22: 12348
A23: Total Capital | B23: =B21+B22 -> 5118618
A24: Weight of Equity | B24: =IF(B23=0,0,B21/B23) -> 0.99758763
A25: Weight of Debt | B25: =IF(B23=0,0,B22/B23) -> 0.0024123699
A26: WACC | B26: =B24*B17+B25*B20 -> 0.11602674
A28: TERMINAL VALUE ASSUMPTION
A29: Terminal Growth Rate | B29: 0.03
A31: VALUATION INPUTS
A32: Current Share Price | B32: 208.76
A33: Diluted Shares Outstanding (millions) | B33: 24460

Sheet Historical Financials
A1: HISTORICAL FINANCIALS ($ in millions)
B3: Year -4 | C3: Year -3 | D3: Year -2 | E3: Year -1 | F3: Year 0 (Base)
A4: Revenue | B4: 26914 | C4: 26974 | D4: 60922 | E4: 130497 | F4: 215938 | H4: Total revenue / net sales.
A5: Revenue Growth % | C5: =IFERROR(C4/B4-1,"") -> 0.002229323 | D5: =IFERROR(D4/C4-1,"") -> 1.2585453 | E5: =IFERROR(E4/D4-1,"") -> 1.1420341 | F5: =IFERROR(F4/E4-1,"") -> 0.65473536 | H5: Formula: Revenue this year / Revenue prior year - 1.
A6: EBIT | B6: 10041 | C6: 4224 | D6: 32972 | E6: 81453 | F6: 130387 | H6: Operating income (earnings before interest and taxes).
A7: EBIT Margin % | B7: =IFERROR(B6/B4,"") -> 0.37307721 | C7: =IFERROR(C6/C4,"") -> 0.15659524 | D7: =IFERROR(D6/D4,"") -> 0.54121664 | E7: =IFERROR(E6/E4,"") -> 0.62417527 | F7: =IFERROR(F6/F4,"") -> 0.60381684 | H7: Formula: EBIT / Revenue.
A8: Effective Tax Rate % | B8: 0.019 | C8: -0.0447 | D8: 0.12 | E8: 0.1326 | F8: 0.1512 | H8: Cash taxes paid / EBIT (or the reported effective tax rate).
A9: Taxes | B9: =B6*B8 -> 190.779 | C9: =C6*C8 -> -188.8128 | D9: =D6*D8 -> 3956.64 | E9: =E6*E8 -> 10800.668 | F9: =F6*F8 -> 19714.514 | H9: Formula: EBIT x Effective Tax Rate.
A10: NOPAT | B10: =B6-B9 -> 9850.221 | C10: =C6-C9 -> 4412.8128 | D10: =D6-D9 -> 29015.36 | E10: =E6-E9 -> 70652.332 | F10: =F6-F9 -> 110672.49 | H10: Formula: EBIT - Taxes (Net Operating Profit After Tax).
A11: D&A | B11: 1174 | C11: 1544 | D11: 1508 | E11: 1864 | F11: 2843 | H11: Depreciation & amortization, from the cash flow statement.
A12: CapEx | B12: 976 | C12: 1833 | D12: 1069 | E12: 3236 | F12: 6042 | H12: Capital expenditures, from the cash flow statement (enter as a positive number).
A13: Increase in Net Working Capital | C13: 1178 | D13: 4516 | E13: 9889 | F13: 13016 | H13: Change in (current assets - current liabilities, excluding cash & debt). Positive = cash outflow.
A14: FCFF | B14: =B10+B11-B12-B13 -> 10048.221 | C14: =C10+C11-C12-C13 -> 2945.8128 | D14: =D10+D11-D12-D13 -> 24938.36 | E14: =E10+E11-E12-E13 -> 59391.332 | F14: =F10+F11-F12-F13 -> 94457.486 | H14: Formula: NOPAT + D&A - CapEx - Increase in NWC (unlevered free cash flow).
A16: Diluted Shares Outstanding | B16: 25350 | C16: 25070 | D16: 24940 | E16: 24804 | F16: 24514 | H16: Weighted-average diluted shares, from the income statement.
A17: Cash & Equivalents | B17: 21208 | C17: 13296 | D17: 25984 | E17: 43210 | F17: 62556 | H17: From the balance sheet.
A18: Total Debt | B18: 11687 | C18: 11855 | D18: 10828 | E18: 9982 | F18: 11040 | H18: Short-term + long-term interest-bearing debt, from the balance sheet.
A19: Net Debt | B19: =B18-B17 -> -9521 | C19: =C18-C17 -> -1441 | D19: =D18-D17 -> -15156 | E19: =E18-E17 -> -33228 | F19: =F18-F17 -> -51516 | H19: Formula: Total Debt - Cash & Equivalents.

Sheet Forecast
A1: FORECAST ($ in millions)
B3: Base (Yr 0) | C3: Year 1 | D3: Year 2 | E3: Year 3 | F3: Year 4 | G3: Year 5
A4: Revenue | B4: ='Historical Financials'!F4 -> 215938 | C4: =B4*(1+C5) -> 345500.8 | D4: =C4*(1+D5) -> 466426.08 | E4: =D4*(1+E5) -> 569039.82 | F4: =E4*(1+F5) -> 654395.79 | G4: =F4*(1+G5) -> 719835.37
A5: Revenue Growth % | B5: ='Historical Financials'!F5 -> 0.65473536 | C5: =Assumptions!B6 -> 0.6 | D5: =Assumptions!C6 -> 0.35 | E5: =Assumptions!D6 -> 0.22 | F5: =Assumptions!E6 -> 0.15 | G5: =Assumptions!F6 -> 0.1
A6: EBIT | B6: ='Historical Financials'!F6 -> 130387 | C6: =C4*Assumptions!B7 -> 210755.49 | D6: =D4*Assumptions!C7 -> 279855.65 | E6: =E4*Assumptions!D7 -> 330043.09 | F6: =F4*Assumptions!E7 -> 366461.64 | G6: =G4*Assumptions!F7 -> 395909.45
A7: EBIT Margin % | B7: ='Historical Financials'!F7 -> 0.60381684 | C7: =IFERROR(C6/C4,"") -> 0.61 | D7: =IFERROR(D6/D4,"") -> 0.6 | E7: =IFERROR(E6/E4,"") -> 0.58 | F7: =IFERROR(F6/F4,"") -> 0.56 | G7: =IFERROR(G6/G4,"") -> 0.55
A8: Tax Rate % | B8: ='Historical Financials'!F8 -> 0.1512 | C8: =Assumptions!B8 -> 0.165 | D8: =Assumptions!C8 -> 0.17 | E8: =Assumptions!D8 -> 0.175 | F8: =Assumptions!E8 -> 0.18 | G8: =Assumptions!F8 -> 0.19
A9: Taxes | B9: ='Historical Financials'!F9 -> 19714.514 | C9: =C6*C8 -> 34774.656 | D9: =D6*D8 -> 47575.46 | E9: =E6*E8 -> 57757.541 | F9: =F6*F8 -> 65963.096 | G9: =G6*G8 -> 75222.796
A10: NOPAT | B10: ='Historical Financials'!F10 -> 110672.49 | C10: =C6-C9 -> 175980.83 | D10: =D6-D9 -> 232280.19 | E10: =E6-E9 -> 272285.55 | F10: =F6-F9 -> 300498.55 | G10: =G6-G9 -> 320686.66
A11: D&A | B11: ='Historical Financials'!F11 -> 2843 | C11: =C4*Assumptions!B10 -> 4837.0112 | D11: =D4*Assumptions!C10 -> 6996.3912 | E11: =E4*Assumptions!D10 -> 9104.6371 | F11: =F4*Assumptions!E10 -> 11124.728 | G11: =G4*Assumptions!F10 -> 12957.037
A12: CapEx | B12: ='Historical Financials'!F12 -> 6042 | C12: =C4*Assumptions!B9 -> 9674.0224 | D12: =D4*Assumptions!C9 -> 13992.782 | E12: =E4*Assumptions!D9 -> 18209.274 | F12: =F4*Assumptions!E9 -> 21595.061 | G12: =G4*Assumptions!F9 -> 25194.238
A13: Increase in Net Working Capital | B13: ='Historical Financials'!F13 -> 13016 | C13: =C4*Assumptions!B11 -> 20730.048 | D13: =D4*Assumptions!C11 -> 25653.434 | E13: =E4*Assumptions!D11 -> 28451.991 | F13: =F4*Assumptions!E11 -> 29447.811 | G13: =G4*Assumptions!F11 -> 28793.415
A14: FCFF | B14: ='Historical Financials'!F14 -> 94457.486 | C14: =C10+C11-C12-C13 -> 150413.77 | D14: =D10+D11-D12-D13 -> 199630.36 | E14: =E10+E11-E12-E13 -> 234728.92 | F14: =F10+F11-F12-F13 -> 260580.4 | G14: =G10+G11-G12-G13 -> 279656.04

Sheet DCF Valuation
A1: DCF VALUATION
B3: Year 1 | C3: Year 2 | D3: Year 3 | E3: Year 4 | F3: Year 5
A4: FCFF | B4: =Forecast!C14 -> 150413.77 | C4: =Forecast!D14 -> 199630.36 | D4: =Forecast!E14 -> 234728.92 | E4: =Forecast!F14 -> 260580.4 | F4: =Forecast!G14 -> 279656.04
A5: Discount Period | B5: 1 | C5: 2 | D5: 3 | E5: 4 | F5: 5
A6: Discount Factor | B6: =1/(1+Assumptions!$B$26)^B5 -> 0.89603588 | C6: =1/(1+Assumptions!$B$26)^C5 -> 0.8028803 | D6: =1/(1+Assumptions!$B$26)^D5 -> 0.71940956 | E6: =1/(1+Assumptions!$B$26)^E5 -> 0.64461678 | F6: =1/(1+Assumptions!$B$26)^F5 -> 0.57759976
A7: PV of FCFF | B7: =B4*B6 -> 134776.14 | C7: =C4*C6 -> 160279.29 | D7: =D4*D6 -> 168866.23 | E7: =E4*E6 -> 167974.5 | F7: =F4*F6 -> 161529.26
A9: Sum of PV of FCFF (Years 1-5) | B9: =SUM(B7:F7) -> 793425.42
A11: TERMINAL VALUE (GORDON GROWTH)
A12: Terminal Year FCFF | B12: =F4*(1+Assumptions!$B$29) -> 288045.72
A13: Terminal Value | B13: =IFERROR(B12/(Assumptions!$B$26-Assumptions!$B$29),"") -> 3348328
A14: Discount Factor (Year 5) | B14: =F6 -> 0.57759976
A15: PV of Terminal Value | B15: =IFERROR(B13*B14,"") -> 1933993.4
A17: ENTERPRISE VALUE TO INTRINSIC VALUE PER SHARE
A18: Enterprise Value | B18: =IFERROR(B9+B15,"") -> 2727418.9
A19: Less: Net Debt | B19: =-'Historical Financials'!F19 -> 51516
A20: Equity Value | B20: =IFERROR(B18+B19,"") -> 2778934.9
A21: Diluted Shares Outstanding | B21: =Assumptions!$B$33 -> 24460
A22: Intrinsic Value per Share | B22: =IFERROR(B20/B21,"") -> 113.6114
A23: Current Market Price | B23: =Assumptions!$B$32 -> 208.76
A24: Upside / (Downside) | B24: =IFERROR(B22/B23-1,"") -> -0.45577984
A26: Check: Terminal Value as % of Enterprise Value | B26: =IFERROR(B15/B18,"") -> 0.70909293

Sheet Sensitivity Analysis
A1: SENSITIVITY ANALYSIS
A2: Output: Intrinsic Value per Share ($) across a range of WACC and Terminal Growth Rate combinations, holding the explicit-period forecast fixed.
A4: Base Case Intrinsic Value / Share | B4: ='DCF Valuation'!B22 -> 113.6114
B6: Terminal Growth Rate →
A7: WACC ↓ | B7: =Assumptions!$B$29+(-0.01) -> 0.02 | C7: =Assumptions!$B$29+(-0.005) -> 0.025 | D7: =Assumptions!$B$29+(0) -> 0.03 | E7: =Assumptions!$B$29+(0.005) -> 0.035 | F7: =Assumptions!$B$29+(0.01) -> 0.04
A8: =Assumptions!$B$26+(-0.01) -> 0.10602674 | B8: {=IFERROR((SUMPRODUCT(Forecast!$C$14:$G$14,1/(1+$A8)^{1,2,3,4,5})+(Forecast!$G$14*(1+B$7))/($A8-B$7)/(1+$A8)^5+'Historical Financials'!$F$19*-1)/Assumptions!$B$33,"n/m")} -> 117.36157 | C8: {=IFERROR((SUMPRODUCT(Forecast!$C$14:$G$14,1/(1+$A8)^{1,2,3,4,5})+(Forecast!$G$14*(1+C$7))/($A8-C$7)/(1+$A8)^5+'Historical Financials'!$F$19*-1)/Assumptions!$B$33,"n/m")} -> 122.84199 | D8: {=IFERROR((SUMPRODUCT(Forecast!$C$14:$G$14,1/(1+$A8)^{1,2,3,4,5})+(Forecast!$G$14*(1+D$7))/($A8-D$7)/(1+$A8)^5+'Historical Financials'!$F$19*-1)/Assumptions!$B$33,"n/m")} -> 129.04326 | E8: {=IFERROR((SUMPRODUCT(Forecast!$C$14:$G$14,1/(1+$A8)^{1,2,3,4,5})+(Forecast!$G$14*(1+E$7))/($A8-E$7)/(1+$A8)^5+'Historical Financials'!$F$19*-1)/Assumptions!$B$33,"n/m")} -> 136.11762 | F8: {=IFERROR((SUMPRODUCT(Forecast!$C$14:$G$14,1/(1+$A8)^{1,2,3,4,5})+(Forecast!$G$14*(1+F$7))/($A8-F$7)/(1+$A8)^5+'Historical Financials'!$F$19*-1)/Assumptions!$B$33,"n/m")} -> 144.26341
A9: =Assumptions!$B$26+(-0.005) -> 0.11102674 | B9: {=IFERROR((SUMPRODUCT(Forecast!$C$14:$G$14,1/(1+$A9)^{1,2,3,4,5})+(Forecast!$G$14*(1+B$7))/($A9-B$7)/(1+$A9)^5+'Historical Financials'!$F$19*-1)/Assumptions!$B$33,"n/m")} -> 110.67492 | C9: {=IFERROR((SUMPRODUCT(Forecast!$C$14:$G$14,1/(1+$A9)^{1,2,3,4,5})+(Forecast!$G$14*(1+C$7))/($A9-C$7)/(1+$A9)^5+'Historical Financials'!$F$19*-1)/Assumptions!$B$33,"n/m")} -> 115.46604 | D9: {=IFERROR((SUMPRODUCT(Forecast!$C$14:$G$14,1/(1+$A9)^{1,2,3,4,5})+(Forecast!$G$14*(1+D$7))/($A9-D$7)/(1+$A9)^5+'Historical Financials'!$F$19*-1)/Assumptions!$B$33,"n/m")} -> 120.84846 | E9: {=IFERROR((SUMPRODUCT(Forecast!$C$14:$G$14,1/(1+$A9)^{1,2,3,4,5})+(Forecast!$G$14*(1+E$7))/($A9-E$7)/(1+$A9)^5+'Historical Financials'!$F$19*-1)/Assumptions!$B$33,"n/m")} -> 126.93885 | F9: {=IFERROR((SUMPRODUCT(Forecast!$C$14:$G$14,1/(1+$A9)^{1,2,3,4,5})+(Forecast!$G$14*(1+F$7))/($A9-F$7)/(1+$A9)^5+'Historical Financials'!$F$19*-1)/Assumptions!$B$33,"n/m")} -> 133.88672
A10: =Assumptions!$B$26+(0) -> 0.11602674 | B10: {=IFERROR((SUMPRODUCT(Forecast!$C$14:$G$14,1/(1+$A10)^{1,2,3,4,5})+(Forecast!$G$14*(1+B$7))/($A10-B$7)/(1+$A10)^5+'Historical Financials'!$F$19*-1)/Assumptions!$B$33,"n/m")} -> 104.68978 | C10: {=IFERROR((SUMPRODUCT(Forecast!$C$14:$G$14,1/(1+$A10)^{1,2,3,4,5})+(Forecast!$G$14*(1+C$7))/($A10-C$7)/(1+$A10)^5+'Historical Financials'!$F$19*-1)/Assumptions!$B$33,"n/m")} -> 108.90556 | D10: {=IFERROR((SUMPRODUCT(Forecast!$C$14:$G$14,1/(1+$A10)^{1,2,3,4,5})+(Forecast!$G$14*(1+D$7))/($A10-D$7)/(1+$A10)^5+'Historical Financials'!$F$19*-1)/Assumptions!$B$33,"n/m")} -> 113.6114 | E10: {=IFERROR((SUMPRODUCT(Forecast!$C$14:$G$14,1/(1+$A10)^{1,2,3,4,5})+(Forecast!$G$14*(1+E$7))/($A10-E$7)/(1+$A10)^5+'Historical Financials'!$F$19*-1)/Assumptions!$B$33,"n/m")} -> 118.89801 | F10: {=IFERROR((SUMPRODUCT(Forecast!$C$14:$G$14,1/(1+$A10)^{1,2,3,4,5})+(Forecast!$G$14*(1+F$7))/($A10-F$7)/(1+$A10)^5+'Historical Financials'!$F$19*-1)/Assumptions!$B$33,"n/m")} -> 124.87999
A11: =Assumptions!$B$26+(0.005) -> 0.12102674 | B11: {=IFERROR((SUMPRODUCT(Forecast!$C$14:$G$14,1/(1+$A11)^{1,2,3,4,5})+(Forecast!$G$14*(1+B$7))/($A11-B$7)/(1+$A11)^5+'Historical Financials'!$F$19*-1)/Assumptions!$B$33,"n/m")} -> 99.301899 | C11: {=IFERROR((SUMPRODUCT(Forecast!$C$14:$G$14,1/(1+$A11)^{1,2,3,4,5})+(Forecast!$G$14*(1+C$7))/($A11-C$7)/(1+$A11)^5+'Historical Financials'!$F$19*-1)/Assumptions!$B$33,"n/m")} -> 103.03307 | D11: {=IFERROR((SUMPRODUCT(Forecast!$C$14:$G$14,1/(1+$A11)^{1,2,3,4,5})+(Forecast!$G$14*(1+D$7))/($A11-D$7)/(1+$A11)^5+'Historical Financials'!$F$19*-1)/Assumptions!$B$33,"n/m")} -> 107.17414 | E11: {=IFERROR((SUMPRODUCT(Forecast!$C$14:$G$14,1/(1+$A11)^{1,2,3,4,5})+(Forecast!$G$14*(1+E$7))/($A11-E$7)/(1+$A11)^5+'Historical Financials'!$F$19*-1)/Assumptions!$B$33,"n/m")} -> 111.79659 | F11: {=IFERROR((SUMPRODUCT(Forecast!$C$14:$G$14,1/(1+$A11)^{1,2,3,4,5})+(Forecast!$G$14*(1+F$7))/($A11-F$7)/(1+$A11)^5+'Historical Financials'!$F$19*-1)/Assumptions!$B$33,"n/m")} -> 116.98951
A12: =Assumptions!$B$26+(0.01) -> 0.12602674 | B12: {=IFERROR((SUMPRODUCT(Forecast!$C$14:$G$14,1/(1+$A12)^{1,2,3,4,5})+(Forecast!$G$14*(1+B$7))/($A12-B$7)/(1+$A12)^5+'Historical Financials'!$F$19*-1)/Assumptions!$B$33,"n/m")} -> 94.426682 | C12: {=IFERROR((SUMPRODUCT(Forecast!$C$14:$G$14,1/(1+$A12)^{1,2,3,4,5})+(Forecast!$G$14*(1+C$7))/($A12-C$7)/(1+$A12)^5+'Historical Financials'!$F$19*-1)/Assumptions!$B$33,"n/m")} -> 97.746324 | D12: {=IFERROR((SUMPRODUCT(Forecast!$C$14:$G$14,1/(1+$A12)^{1,2,3,4,5})+(Forecast!$G$14*(1+D$7))/($A12-D$7)/(1+$A12)^5+'Historical Financials'!$F$19*-1)/Assumptions!$B$33,"n/m")} -> 101.41167 | E12: {=IFERROR((SUMPRODUCT(Forecast!$C$14:$G$14,1/(1+$A12)^{1,2,3,4,5})+(Forecast!$G$14*(1+E$7))/($A12-E$7)/(1+$A12)^5+'Historical Financials'!$F$19*-1)/Assumptions!$B$33,"n/m")} -> 105.47967 | F12: {=IFERROR((SUMPRODUCT(Forecast!$C$14:$G$14,1/(1+$A12)^{1,2,3,4,5})+(Forecast!$G$14*(1+F$7))/($A12-F$7)/(1+$A12)^5+'Historical Financials'!$F$19*-1)/Assumptions!$B$33,"n/m")} -> 110.02056
A14: Reading the table
A15: Each cell independently recomputes enterprise value using the fixed 5-year FCFF forecast, discounted at that row's WACC, plus a terminal value built with that column's growth rate. Net Debt and Share Count stay constant. The center cell should equal the base case above.

Sheet Charts
A1: CHARTS
A4: CHART DATA
A5: Period | B5: Yr -4 | C5: Yr -3 | D5: Yr -2 | E5: Yr -1 | F5: Yr 0 | G5: Yr 1 | H5: Yr 2 | I5: Yr 3 | J5: Yr 4 | K5: Yr 5
A6: Revenue | B6: ='Historical Financials'!B4 -> 26914 | C6: ='Historical Financials'!C4 -> 26974 | D6: ='Historical Financials'!D4 -> 60922 | E6: ='Historical Financials'!E4 -> 130497 | F6: ='Historical Financials'!F4 -> 215938 | G6: =Forecast!C4 -> 345500.8 | H6: =Forecast!D4 -> 466426.08 | I6: =Forecast!E4 -> 569039.82 | J6: =Forecast!F4 -> 654395.79 | K6: =Forecast!G4 -> 719835.37
A7: FCFF | B7: ='Historical Financials'!B14 -> 10048.221 | C7: ='Historical Financials'!C14 -> 2945.8128 | D7: ='Historical Financials'!D14 -> 24938.36 | E7: ='Historical Financials'!E14 -> 59391.332 | F7: ='Historical Financials'!F14 -> 94457.486 | G7: =Forecast!C14 -> 150413.77 | H7: =Forecast!D14 -> 199630.36 | I7: =Forecast!E14 -> 234728.92 | J7: =Forecast!F14 -> 260580.4 | K7: =Forecast!G14 -> 279656.04
A9: Valuation Comparison
A10: Intrinsic Value / Share | B10: ='DCF Valuation'!B22 -> 113.6114
A11: Current Market Price | B11: ='DCF Valuation'!B23 -> 208.76
